[
    {
        "id": "41300fac-80a2-4ae7-a4e9-58aa7eb2d9cd",
        "content": "# Спецификация\n## Компонент IEcoDateTime1\nСтатус: Черновик\nДата: Ноябрь 8, 2021\nВерсия: 1.0\n## Обзор\nДанный документ описывает требования к реализации компонента Eco.DateTime1.\n## Введение\nОписание.\n## Примечание\nКлючевые слова в документе\n## Ссылки\nДанный параграф содержит ссылки на информацию, помогающую понять данный документ: \n[] – наименование ссылки\nДоступен по: http://адрес\n## Компонент Eco. DateTime1\n\nКомпонент. \nКомпонент, имеет следующие описание:\n### IEcoDateTime1 описание на ECO IDL\n#### Функция Now\n#### Функция возвращает объект DateTime, которому присвоены текущие дата и время данного компьютера, выраженные как местное время.\n#### Функция Clone\n#### Функция Функция get_SystemTime\n#### Функция получает выбранное в данный момент время из элемента управления выбора даты и времени (DTP) и помещает его в указанную структуру SYSTEMTIME.\n#### Функция set_SystemTime\n#### Функция задает для элемента управления выбора даты и времени (DTP) заданные дату и время.\n#### Функция get_TimeOfDaySec\n\nФункция.\n#### Функция get_TimeOfDayUSec\n\nФункция.\n#### Функция ToString\n#### Функция преобразует значение текущего объекта DateTime в эквивалентное ему строковое представление.\n#### Функция ToStringFormat\n#### Функция преобразует значение текущего объекта DateTime в эквивалентное ему строковое представление с использованием указанных сведений о форматировании, связанных с языком и региональными параметрами.\n## Коды ошибок\n\nСледующая таблица содержит коды ошибок.\n## Приложение А: Обучающие программы\n\n",
        "metadata": {
            "title": "Спецификация",
            "version": "1.0",
            "component": "IEcoDateTime1",
            "overview": "Данный документ описывает требования к реализации компонента Eco.DateTime1.",
            "author": "",
            "date": "Ноябрь 8, 2021"
        }
    },
    {
        "id": "5bece487-3d06-43fb-a791-31ae3fb7277c",
        "content": "# Спецификация\n## Компонент IEcoLog1\nСтатус: Черновик\nДата: Ноябрь 8, 2021\nВерсия: 1.0\n## Обзор\nДанный документ описывает требования к реализации компонента Eco.Log1.\n## Введение\nОписание.\n## Примечание\nКлючевые слова в документе\n## Ссылки\nДанный параграф содержит ссылки на информацию, помогающую понять данный документ: \n[] – наименование ссылки\nДоступен по: http://адрес\n## Компонент Eco. Log1\n\nКомпонент. \nКомпонент, имеет следующие описание:\n## Интерфейс IEcoLog1\n### IEcoLog1 описание на ECO IDL\n#### Функция AddAffiliate\n#### Функция Функция set_LevelMask\n#### Функция Функция get_LevelMask\n#### Функция Функция Debug\n#### Функция Функция Info\n#### Функция Функция Warn\n#### Функция Функция Error\n#### Функция Функция Fatal\n#### Функция Функция DebugFormat\n#### Функция Функция InfoFormat\n#### Функция Функция recvmmsg\n#### Функция Функция WarnFormat\n#### Функция Функция ErrorFormat\n#### Функция Функция FatalFormat\n#### Функция Функция HexDump\n#### Функция Функция BinDump\n#### Функция ## Интерфейс IEcoLog1Affiliate\n### IEcoLog1Affiliate описание на ECO IDL\n#### Функция get_Name\n#### Функция Функция get_Layout\n#### Функция Функция set_Layout\n#### Функция Функция Write\n#### Функция ## Интерфейс IEcoLog1Layout\n### IEcoLog1Layout описание на ECO IDL\n#### Функция get_Name\n#### Функция Функция Format\n#### Функция ## Интерфейс IEcoLog1ConsoleAffiliate\n### IEcoLog1ConsoleAffiliate описание на ECO IDL\n#### Функция get_TargetOutput\n#### Функция Функция set_TargetOutput\n#### Функция ## Интерфейс IEcoLog1FileAffiliate\n### IEcoLog1FileAffiliate описание на ECO IDL\n#### Функция get_FileName\n#### Функция Функция set_FileName\n#### Функция ## Интерфейс IEcoLog1SimpleLayout\n### IEcoLog1SimpleLayout описание на ECO IDL\n#### Функция get_Pattern\n#### Функция Функция set_Pattern\n#### Функция ## Коды ошибок\n\nСледующая таблица содержит коды ошибок.\n## Приложение А: Обучающие программы\n\n",
        "metadata": {
            "title": "Спецификация",
            "version": "1.0",
            "component": "IEcoLog1",
            "overview": "Данный документ описывает требования к реализации компонента Eco.Log1.",
            "author": "",
            "date": "Ноябрь 8, 2021"
        }
    },
    {
        "id": "af040a2f-1c05-435d-b980-cc93bc35118e",
        "content": "# Спецификация\n## Компонент IEcoSocketP02\nСтатус: Черновик\nДата: Ноябрь 8, 2021\nВерсия: 1.0\n## Обзор\nДанный документ описывает требования к реализации компонента Eco.SocketP02.\n## Введение\nОписание.\n## Примечание\nКлючевые слова в документе\n## Ссылки\nДанный параграф содержит ссылки на информацию, помогающую понять данный документ: \n[] – наименование ссылки\nДоступен по: http://адрес\n## Компонент Eco. SocketP02\n\nКомпонент. \nКомпонент, имеет следующие описание:\n## Интерфейс IEcoSocketP02\n### IEcoSocketP02 описание на ECO IDL\n#### Функция accept\n#### Функция разрешает входящую попытку подключения к сокету.\n#### Функция bind\n#### Функция связывает локальный адрес с сокетом.\n#### Функция connect\n#### Функция устанавливает соединение с указанным сокетом.\n#### Функция getpeername\n#### Функция извлекает адрес однорангового узла, к которому подключен сокет.\n#### Функция getsockname\n#### Функция извлекает локальное имя сокета.\n#### Функция getsockopt\n#### Функция извлекает параметр сокета.\n#### Функция listen\n#### Функция помещает сокет в состояние, в котором он прослушивает входящее соединение.\n#### Функция recv\n#### Функция получает данные из подключенного сокета или связанного сокета без установления соединения.\n#### Функция recvfrom\n#### Функция получает дейтаграмму и сохраняет адрес источника.\n#### Функция recvmsg\n#### Функция получает сообщения на сокете с дескриптором сокета и сохраняет их в массиве заголовков сообщений.\n#### Функция recvmmsg\n#### Функция Функция send\n#### Функция отправляет данные в подключенный сокет.\n#### Функция sendto\n#### Функция отправляет данные в определенное место назначения.\n#### Функция sendmsg\n#### Функция отправляет сообщения на сокет.\n#### Функция sendmmsg\n#### Функция отправляет несколько сообщений в сокет.\n#### Функция setsockopt\n#### Функция задает параметр сокета.\n#### Функция shutdown\n#### Функция отключает отправку или получение данных на сокете.\n#### Функция sockatmark\n#### Функция определяет, есть ли в сокете отметка о внеполосных данных.\n#### Функция socket\n#### Функция создает конечную точку для связи и возвращает файловый дескриптор для сокета.\n#### Функция socketpair\n#### Функция получает пару сокетов указанного типа, которые не имеют имени и подключены в указанном домене и используют указанный протокол.\n## Интерфейс IEcoINetP02\n### IEcoINetP02 описание на ECO IDL\n#### Функция htonl\n#### Функция возвращает значение в сетевом порядке байтов TCP/IP’s.\n#### Функция htons\n#### Функция возвращает значение в сетевом порядке байтов TCP/IP.\n#### Функция ntohl\n#### Функция преобразует u_long из сетевого порядка байтов TCP/IP в порядок байтов хоста.\n#### Функция ntohs\n#### Функция преобразует u_short из сетевого порядка байтов TCP/IP в порядок байтов хоста.\n#### Функция inet_addr\n#### Функция преобразует строку, содержащую десятичный адрес IPv4 с точками, в правильный адрес для структуры IN_ADDR.\n#### Функция inet_ntoa\n#### Функция преобразует интернет-адрес (Ipv4) в строку ASCII в стандартном интернет-десятичном формате.\n#### Функция inet_ntop\n#### Функция преобразует интернет-адрес IPv4 или IPv6 в строку в стандартном формате Интернета.\n#### Функция inet_pton\n#### Функция преобразует сетевой адрес IPv4 или IPv6 в стандартной форме представления текста в числовую двоичную форму.\n## Коды ошибок\n\nСледующая таблица содержит коды ошибок.\n## Приложение А: Обучающие программы\n\n",
        "metadata": {
            "title": "Спецификация",
            "version": "1.0",
            "component": "IEcoSocketP02",
            "overview": "Данный документ описывает требования к реализации компонента Eco.SocketP02.",
            "author": "",
            "date": "Ноябрь 8, 2021"
        }
    }
]